{
	"name": "R (via rig)",
	"id": "r-rig",
	"version": "0.3.0",
	"description": "Installs R, rig, some R packages, and needed dependencies. Note: May require source code compilation for R packages.",
	"options": {
		"version": {
			"type": "string",
			"proposals": [
				"release",
				"none"
			],
			"default": "release",
			"description": "Select version of R, if not the latest release version."
		},
		"installRMarkdown": {
			"type": "boolean",
			"default": false,
			"description": "Install the rmarkdown R package."
		},
		"pandocVersion": {
			"type": "string",
			"proposals": [
				"auto",
				"none",
				"os-provided",
				"latest"
			],
			"default": "auto",
			"description": "Select version of Pandoc. By default, the latest version is installed if needed."
		}
	},
	"customizations": {
		"vscode": {
			"extensions": [
				"REditorSupport.r"
			],
			"settings": {
				"[r]": {
					"editor.wordSeparators": "`~!@#%$^&*()-=+[{]}\\|;:'\",<>/?"
				}
			}
		}
	}
}
